mahdi_brightness_controller/__init__.py
mahdi_brightness_controller/gui.py
mahdi_brightness_controller-1.0.2.dist-info/licenses/LICENSE
mahdi_brightness_controller-1.0.2.dist-info/METADATA
mahdi_brightness_controller-1.0.2.dist-info/WHEEL
mahdi_brightness_controller-1.0.2.dist-info/entry_points.txt
mahdi_brightness_controller-1.0.2.dist-info/top_level.txt
mahdi_brightness_controller-1.0.2.dist-info/RECORD
