Metadata-Version: 2.4
Name: mahdi-brightness-controller
Version: 1.0.2
Summary: A Linux display brightness and night mode controller using tkinter
Home-page: https://github.com/oxl-mahdi/mahdi-brightness-controller
Author: Muahammd Mahdi Hasan
Author-email: mhasan3608@gmail.com
Classifier: Programming Language :: Python :: 3
Classifier: License :: OSI Approved :: MIT License
Classifier: Operating System :: POSIX :: Linux
Requires-Python: >=3.6
License-File: LICENSE
Dynamic: author
Dynamic: author-email
Dynamic: classifier
Dynamic: description
Dynamic: description-content-type
Dynamic: home-page
Dynamic: license-file
Dynamic: requires-python
Dynamic: summary
